setup.py
nlplib/__init__.py
nlplib/base.py
nlplib.egg-info/PKG-INFO
nlplib.egg-info/SOURCES.txt
nlplib.egg-info/dependency_links.txt
nlplib.egg-info/requires.txt
nlplib.egg-info/top_level.txt