Metadata-Version: 1.0
Name: nlplib
Version: 0.0.1
Summary: Python client library for langid
Home-page: https://github.com/td391/nlplib
Author: td391
Author-email: td39@gmx.com
License: MIT
Platform: any
